{"cameraMode":{"drawMode":0,"name":"Shaded","section":"Shading Mode"},"sceneLighting":true,"audioPlay":false,"sceneViewState":{"showFog":true,"showMaterialUpdate":false,"showSkybox":true,"showFlares":true,"showImageEffects":true,"showParticleSystems":true,"showVisualEffectGraphs":true,"m_FxEnabled":true},"in2DMode":false,"pivot":{"x":-30.024824142456056,"y":-0.6578735709190369,"z":5.839755058288574},"rotation":{"x":-0.0403783842921257,"y":0.6762230396270752,"z":-0.03715822845697403,"w":-0.7346476316452026},"size":14.458518981933594,"orthographic":false}